get_the_hell_out_of_here/README.MD
get_the_hell_out_of_here/__init__.py
get_the_hell_out_of_here/requirements.txt
get_the_hell_out_of_here/thirdparty.json
get_the_hell_out_of_here-0.12.dist-info/LICENSE.rst
get_the_hell_out_of_here-0.12.dist-info/METADATA
get_the_hell_out_of_here-0.12.dist-info/WHEEL
get_the_hell_out_of_here-0.12.dist-info/top_level.txt
get_the_hell_out_of_here-0.12.dist-info/RECORD
